trivialapi/fleetdm/core.py
trivialapi/toda/commodity.py
trivialapi/toda/core.py
trivialapi/toda/payment.py
trivialapi/toda/token.py
trivialapi/toda/twin.py
trivialapi/toda/util.py
trivialapi/unified/core.py
trivialapi-0.0.39.dist-info/METADATA
trivialapi-0.0.39.dist-info/WHEEL
trivialapi-0.0.39.dist-info/top_level.txt
trivialapi-0.0.39.dist-info/RECORD
