Metadata-Version: 2.4
Name: trivialapi
Version: 0.0.39
Summary: A trivial set of API bindings for things I use. So far, TODA and FleetDM
Author-email: inaimathi <leo.zovic@gmail.com>
Project-URL: Homepage, https://github.com/inaimathi/trivialapi
Project-URL: Issues, https://github.com/inaimathi/trivialapi/issues
Classifier: Programming Language :: Python :: 3
Classifier: License :: OSI Approved :: MIT License
Classifier: Operating System :: OS Independent
Requires-Python: >=3.8
Requires-Dist: requests
Requires-Dist: pyyaml
